polycephaly/__init__.py
polycephaly/conftest.py
polycephaly/log.py
polycephaly/comms/__init__.py
polycephaly/comms/messenger/__init__.py
polycephaly/comms/messenger/actions.py
polycephaly/comms/messenger/filters.py
polycephaly/comms/messenger/info.py
polycephaly/comms/messenger/setup.py
polycephaly/comms/messenger/test/__init__.py
polycephaly/comms/messenger/test/test_filtering.py
polycephaly/comms/messenger/test/test_init.py
polycephaly/comms/messenger/test/test_queues.py
polycephaly/comms/messenger/test/test_transport.py
polycephaly/core/__init__.py
polycephaly/core/application/__init__.py
polycephaly/core/application/actions.py
polycephaly/core/application/events.py
polycephaly/core/application/info.py
polycephaly/core/application/setup.py
polycephaly/core/application/timing.py
polycephaly/core/process/__init__.py
polycephaly/core/process/actions.py
polycephaly/core/process/events.py
polycephaly/core/process/info.py
polycephaly/core/process/locking.py
polycephaly/core/process/setup.py
polycephaly/core/process/signals.py
polycephaly/core/process/threading.py
polycephaly/core/process/timing.py
polycephaly/core/process/main/__init__.py
polycephaly/core/process/main/callbacks.py
polycephaly/core/process/messaging/__init__.py
polycephaly/core/process/messaging/actions.py
polycephaly/core/process/messaging/filters.py
polycephaly/core/process/messaging/info.py
polycephaly/core/process/messaging/setup.py
polycephaly/functions/__init__.py
polycephaly/functions/dynamic.py
polycephaly/functions/threading.py
polycephaly/functions/utilities.py
polycephaly/processes/__init__.py
Polycephaly-2019.11a5.dist-info/LICENSE
Polycephaly-2019.11a5.dist-info/METADATA
Polycephaly-2019.11a5.dist-info/WHEEL
Polycephaly-2019.11a5.dist-info/top_level.txt
Polycephaly-2019.11a5.dist-info/RECORD
