Metadata-Version: 2.1
Name: Polycephaly
Version: 2019.11a5
Summary: Easily create system daemons (and programs) that use an email-like syntax for communicating between threaded and forked processes.
Home-page: https://gitlab.com/ltgiv/polycephaly
Author: Louis T. Getterman IV
Author-email: Thad.Getterman@gmail.com
License: MIT
Project-URL: Documentation, https://ltgiv.gitlab.io/polycephaly/
Project-URL: Source, https://gitlab.com/ltgiv/polycephaly
Project-URL: Tracker, https://gitlab.com/ltgiv/polycephaly/issues
Platform: UNKNOWN
Classifier: Programming Language :: Python :: 3
Classifier: License :: OSI Approved :: MIT License
Classifier: Operating System :: POSIX
Requires-Dist: Logbook
